Metadata-Version: 2.1
Name: fs-gcsfs
Version: 1.4.2
Summary: A PyFilesystem interface to Google Cloud Storage
Home-page: https://github.com/Othoz/gcsfs
Author: Othoz GmbH
Author-email: wiesner@othoz.com
License: MIT
Project-URL: Bug Tracker, https://github.com/Othoz/gcsfs/issues
Project-URL: Documentation, http://fs-gcsfs.readthedocs.io/en/latest/
Keywords: pyfilesystem,filesystem,google,gcs,google cloud storage
Platform: UNKNOWN
Classifier: Development Status :: 4 - Beta
Classifier: Intended Audience :: Developers
Classifier: License :: OSI Approved :: MIT License
Classifier: Operating System :: OS Independent
Classifier: Programming Language :: Python
Classifier: Programming Language :: Python :: 3
Classifier: Programming Language :: Python :: 3.5
Classifier: Programming Language :: Python :: 3.6
Classifier: Programming Language :: Python :: 3.7
Classifier: Programming Language :: Python :: 3.8
Classifier: Programming Language :: Python :: Implementation
Classifier: Topic :: System :: Filesystems
Requires-Python: >=3.5
